pedanlib/__init__.py
pedanlib/src/CanRisk/canrisk.py
pedanlib/src/CanRisk/data/canrisk.json
pedanlib/src/Coseg/coseg.py
pedanlib/src/Coseg/data/risk1_lognormal.csv
pedanlib/src/Coseg/data/risk1_lognormal_pr_v02.csv
pedanlib/src/Coseg/data/risk1_lognormal_pr_v03.csv
pedanlib/src/Coseg/util.py
pedanlib/src/Pedigree/pedigree.py
pedanlib-1.0.6.dist-info/METADATA
pedanlib-1.0.6.dist-info/WHEEL
pedanlib-1.0.6.dist-info/RECORD
